README.rst
setup.py
mvs_rpc/__init__.py
mvs_rpc/common.py
mvs_rpc/mvs_api.py
mvs_rpc.egg-info/PKG-INFO
mvs_rpc.egg-info/SOURCES.txt
mvs_rpc.egg-info/dependency_links.txt
mvs_rpc.egg-info/requires.txt
mvs_rpc.egg-info/top_level.txt