Metadata-Version: 1.1
Name: mvs-rpc
Version: 0.1.0
Summary: python implement of mvs rpc
Home-page: https://github.com/mvshub/mvs_rpc_python.git
Author: chengzhpchn
Author-email: chengzhpchn@163.com
License: MIT License
Keywords: mvs sdk,mvs client
Platform: all
Classifier: Development Status :: 3 - Alpha
Classifier: Intended Audience :: Developers
Classifier: Topic :: Software Development :: Libraries
Classifier: License :: OSI Approved :: MIT License
Classifier: Programming Language :: Python :: 2
Classifier: Programming Language :: Python :: 2.6
Classifier: Programming Language :: Python :: 2.7
